{
  "cli": {
    "version": ">= 7.6.0",
    "appVersionSource": "remote"
  },
  "build": {
    "development": {
      "node": "22.11.0",
      "developmentClient": true,
      "distribution": "internal",
      "ios": {
        "simulator": true
      },
      "env": {
      }
    },
    "preview": {
      "node": "22.11.0",
      "android": {
        "buildType": "apk",
        "env": {}
      },
      "distribution":"internal"
    },
    "production": {
      "node": "22.11.0",
      "autoIncrement": true,
      "android": {
        "env": {}
      },
      "ios": {}
    }
  },
  "submit": {
    "devRevision": {},
    "production": {}
  }
}
